mortgagekit/__init__.py
mortgagekit/calculator.py
mortgagekit/constants.py
mortgagekit/utils.py
py_mortgagekit-1.0.3b1.dist-info/DESCRIPTION.rst
py_mortgagekit-1.0.3b1.dist-info/METADATA
py_mortgagekit-1.0.3b1.dist-info/RECORD
py_mortgagekit-1.0.3b1.dist-info/WHEEL
py_mortgagekit-1.0.3b1.dist-info/metadata.json
py_mortgagekit-1.0.3b1.dist-info/top_level.txt
