Metadata-Version: 2.0
Name: py-mortgagekit
Version: 1.0.3b1
Summary: Python library for mortgage calculations.
Home-page: https://github.com/MikaSoftware/py-mortgagekit
Author: Bartlomiej Mika
Author-email: bart@mikasoftware.com
License: BSD 2-Clause License
Keywords: mortgage amortization finance
Platform: UNKNOWN
Classifier: Development Status :: 4 - Beta
Classifier: Intended Audience :: Education
Classifier: License :: OSI Approved :: BSD License
Classifier: Natural Language :: English
Classifier: Programming Language :: Python :: 3.6
Classifier: Topic :: Office/Business :: Financial :: Accounting
Requires-Python: >=3.6
Requires-Dist: py-moneyed
Requires-Dist: python-dateutil
